pyenbc/__init__.py
pyenbc/file_helper/__init__.py
pyenbc/file_helper/content_helper.py
pyenbc/file_helper/decompress_helper.py
pyenbc/file_helper/format_helper.py
pyenbc/file_helper/jython_helper.py
pyenbc/file_helper/magic_file.py
pyenbc/file_helper/maven_helper.py
pyenbc/file_helper/pig_helper.py
pyenbc/remote/__init__.py
pyenbc/remote/azure_connection.py
pyenbc/remote/azure_drive.py
pyenbc/remote/azure_exception.py
pyenbc/remote/azure_transfer_api.py
pyenbc/remote/cloud_transfer.py
pyenbc/remote/magic_azure.py
pyenbc/remote/magic_remote_ssh.py
pyenbc/remote/ssh_remote_connection.py
pyenbc-1.2.4.dist-info/DESCRIPTION.rst
pyenbc-1.2.4.dist-info/METADATA
pyenbc-1.2.4.dist-info/RECORD
pyenbc-1.2.4.dist-info/WHEEL
pyenbc-1.2.4.dist-info/metadata.json
pyenbc-1.2.4.dist-info/top_level.txt
