Metadata-Version: 2.0
Name: pyenbc
Version: 1.2.4
Summary: Simplifies remote access to clusters.
Home-page: http://www.xavierdupre.fr/app/pyenbc/helpsphinx/index.html
Author: Xavier Dupré
Author-email: xavier.dupre@gmail.com
License: MIT
Download-URL: https://github.com/sdpython/pyenbc/
Keywords: pyenbc,cluster,Hadoop,PIG,HIVE
Platform: UNKNOWN
Classifier: Programming Language :: Python :: 3
Classifier: Intended Audience :: Developers
Classifier: Topic :: Scientific/Engineering
Classifier: Topic :: Education
Classifier: License :: OSI Approved :: MIT License
Classifier: Development Status :: 5 - Production/Stable
Requires-Dist: pyquickhelper (>=1.5.2259)
Provides-Extra: remote.azure_connection
Requires-Dist: azure; extra == 'remote.azure_connection'
Provides-Extra: remote.ssh_remote_connection
Requires-Dist: paramiko; extra == 'remote.ssh_remote_connection'
Requires-Dist: ansiconv; extra == 'remote.ssh_remote_connection'
Requires-Dist: ansi2html; extra == 'remote.ssh_remote_connection'
Requires-Dist: chardet; extra == 'remote.ssh_remote_connection'
